setup.py
sphinxcontrib/__init__.py
sphinxcontrib/coffeedomain/__init__.py
sphinxcontrib/coffeedomain/documenters.py
sphinxcontrib/coffeedomain/domain.py
sphinxcontrib_coffee.egg-info/PKG-INFO
sphinxcontrib_coffee.egg-info/SOURCES.txt
sphinxcontrib_coffee.egg-info/dependency_links.txt
sphinxcontrib_coffee.egg-info/namespace_packages.txt
sphinxcontrib_coffee.egg-info/top_level.txt