Metadata-Version: 1.0
Name: sphinxcontrib-coffee
Version: 0.1.1
Summary: Sphinx extension to add CoffeeScript support
Home-page: UNKNOWN
Author: Stephen Sugden
Author-email: glurgle@gmail.com
License: BSD
Platform: any
